spotify_history_reader/__init__.py
spotify_history_reader/core.py
spotify_history_reader/reader.py
spotify_history_reader-0.1.2.dist-info/METADATA
spotify_history_reader-0.1.2.dist-info/WHEEL
spotify_history_reader-0.1.2.dist-info/RECORD
