Metadata-Version: 2.1
Name: spotify-history-reader
Version: 0.1.2
Summary: 
Author: Andrew Wells
Author-email: ajwells128@gmail.com
Requires-Python: >=3.10,<4.0
Classifier: Programming Language :: Python :: 3
Classifier: Programming Language :: Python :: 3.10
Classifier: Programming Language :: Python :: 3.11
Classifier: Programming Language :: Python :: 3.12
Classifier: Programming Language :: Python :: 3.13
